imio.smartweb.policy-1.2.15-py3.13-nspkg.pth
imio/smartweb/policy/__init__.py
imio/smartweb/policy/caching.py
imio/smartweb/policy/caching.zcml
imio/smartweb/policy/configure.zcml
imio/smartweb/policy/interfaces.py
imio/smartweb/policy/monkey.py
imio/smartweb/policy/permissions.zcml
imio/smartweb/policy/profiles.zcml
imio/smartweb/policy/setupdemo.py
imio/smartweb/policy/setuphandlers.py
imio/smartweb/policy/subscribers.zcml
imio/smartweb/policy/testing.py
imio/smartweb/policy/utils.py
imio/smartweb/policy/viewlets.zcml
imio/smartweb/policy/browser/__init__.py
imio/smartweb/policy/browser/configure.zcml
imio/smartweb/policy/browser/faceted/__init__.py
imio/smartweb/policy/browser/faceted/configure.zcml
imio/smartweb/policy/browser/faceted/subtyper.py
imio/smartweb/policy/browser/overrides/.gitkeep
imio/smartweb/policy/browser/static/.gitkeep
imio/smartweb/policy/profiles/default/browserlayer.xml
imio/smartweb/policy/profiles/default/controlpanel.xml
imio/smartweb/policy/profiles/default/metadata.xml
imio/smartweb/policy/profiles/default/rolemap.xml
imio/smartweb/policy/profiles/default/viewlets.xml
imio/smartweb/policy/profiles/default/registry/autopublishing.xml
imio/smartweb/policy/profiles/default/registry/autoscaling.xml
imio/smartweb/policy/profiles/default/registry/caching.xml
imio/smartweb/policy/profiles/default/registry/messagesviewlet.xml
imio/smartweb/policy/profiles/default/registry/smartweb.xml
imio/smartweb/policy/profiles/default/types/Collection.xml
imio/smartweb/policy/profiles/default/types/Document.xml
imio/smartweb/policy/profiles/default/types/Event.xml
imio/smartweb/policy/profiles/default/types/File.xml
imio/smartweb/policy/profiles/default/types/Folder.xml
imio/smartweb/policy/profiles/default/types/Image.xml
imio/smartweb/policy/profiles/default/types/Link.xml
imio/smartweb/policy/profiles/default/types/News_Item.xml
imio/smartweb/policy/profiles/default/types/Plone_Site.xml
imio/smartweb/policy/profiles/demo/metadata.xml
imio_smartweb_policy-1.2.15.dist-info/licenses/LICENSE.GPL
imio_smartweb_policy-1.2.15.dist-info/licenses/LICENSE.rst
imio_smartweb_policy-1.2.15.dist-info/METADATA
imio_smartweb_policy-1.2.15.dist-info/WHEEL
imio_smartweb_policy-1.2.15.dist-info/namespace_packages.txt
imio_smartweb_policy-1.2.15.dist-info/top_level.txt
imio_smartweb_policy-1.2.15.dist-info/RECORD
